Metadata-Version: 2.1
Name: jk-interprocesssync
Version: 0.2020.4.1
Summary: This python module provides simple synchronization and data transfer mechanisms for processes residing on the same host.
Home-page: https://github.com/jkpubsrc/python-module-jk-interprocessync
Author: Jürgen Knauth
Author-email: pubsrc@binary-overflow.de
License: Apache 2.0
Download-URL: https://github.com/jkpubsrc/python-module-jk-interprocessync/tarball/0.2020.4.1
Keywords: interprocess,synchronization,ipc
Platform: UNKNOWN
Classifier: Development Status :: 3 - Alpha
Classifier: License :: OSI Approved :: Apache Software License
